terminal_karaoke/__init__.py
terminal_karaoke/__main__.py
terminal_karaoke/audio.py
terminal_karaoke/downloader.py
terminal_karaoke/lyrics.py
terminal_karaoke/main.py
terminal_karaoke/player.py
terminal_karaoke/ui.py
terminal_karaoke-1.0.4.dist-info/licenses/LICENSE
terminal_karaoke-1.0.4.dist-info/METADATA
terminal_karaoke-1.0.4.dist-info/WHEEL
terminal_karaoke-1.0.4.dist-info/entry_points.txt
terminal_karaoke-1.0.4.dist-info/top_level.txt
terminal_karaoke-1.0.4.dist-info/RECORD
