Metadata-Version: 2.4
Name: terminal-karaoke
Version: 1.0.4
Summary: A terminal-based karaoke player
Home-page: https://github.com/hissterical/terminal-karaoke
Author: Dexter Morgan
Author-email: Dexter Morgan <paarivah@proton.me>
License: MIT
Project-URL: Homepage, https://github.com/hissterical/terminal-karaoke
Project-URL: Bug Tracker, https://github.com/hissterical/terminal-karaoke/issues
Classifier: Development Status :: 4 - Beta
Classifier: Intended Audience :: End Users/Desktop
Classifier: License :: OSI Approved :: MIT License
Classifier: Operating System :: OS Independent
Classifier: Programming Language :: Python :: 3
Classifier: Programming Language :: Python :: 3.9
Classifier: Programming Language :: Python :: 3.10
Classifier: Programming Language :: Python :: 3.11
Classifier: Programming Language :: Python :: 3.12
Requires-Python: >=3.9
License-File: LICENSE
Requires-Dist: beautifulsoup4>=4.13.5
Requires-Dist: pygame>=2.6.1
Requires-Dist: requests>=2.32.5
Requires-Dist: windows-curses>=2.3.0; platform_system == "Windows"
Requires-Dist: yt-dlp>=2025.8.27
Dynamic: author
Dynamic: home-page
Dynamic: license-file
Dynamic: requires-python
